{
    "accounts": {
        "68723771756638": {
            "crew_id": 468151451274,
            "crew_name": "Oncilla",
            "gender": 1,
            "last_seen": 1758793559,
            "name": "PaRaNo¡D",
            "registered": "Aug 12, 2022, 7:43:12 PM",
            "role_id": 68723771756638,
            "server_region": "southeast_asia"
        },
        "68728066681776": {
            "crew_id": 201863478913,
            "crew_name": "Solo Play PH",
            "gender": 1,
            "last_seen": 1758793559,
            "name": "_Lilla_",
            "registered": "Aug 11, 2022, 12:33:49 PM",
            "role_id": 68728066681776,
            "server_region": "southeast_asia"
        },
        "68732361721345": {
            "crew_id": 2516850851459,
            "crew_name": "Schwarz Studio",
            "gender": 1,
            "last_seen": 1758793559,
            "name": "Inorinae",
            "registered": "Aug 16, 2022, 2:46:16 PM",
            "role_id": 68732361721345,
            "server_region": "southeast_asia"
        },
        "68758131441868": {
            "crew_id": 2314987388549,
            "crew_name": "Waifu",
            "gender": 1,
            "last_seen": 1758793559,
            "name": "Yuzukiii",
            "registered": "Aug 11, 2022, 7:33:55 AM",
            "role_id": 68758131441868,
            "server_region": "southeast_asia"
        },
        "68762426451807": {
            "crew_id": 206158446212,
            "crew_name": "CASTLE",
            "gender": 1,
            "last_seen": 1758793559,
            "name": "eScaρe",
            "registered": "Aug 12, 2022, 7:00:12 AM",
            "role_id": 68762426451807,
            "server_region": "southeast_asia"
        },
        "68775311317152": {
            "crew_id": 184683609733,
            "crew_name": "Guardian",
            "gender": 1,
            "last_seen": 1758793559,
            "name": "Rim",
            "registered": "Aug 11, 2022, 10:09:21 AM",
            "role_id": 68775311317152,
            "server_region": "southeast_asia"
        },
        "68775311752295": {
            "crew_id": 0,
            "crew_name": "",
            "gender": 0,
            "last_seen": 1758793559,
            "name": "Deception02",
            "registered": "Sep 25, 2025, 1:16:25 PM",
            "role_id": 68775311752295,
            "server_region": "southeast_asia"
        },
        "68779606308489": {
            "crew_id": 365072236176,
            "crew_name": "Fairy Tail",
            "gender": 1,
            "last_seen": 1758793559,
            "name": "Aruf",
            "registered": "Aug 11, 2022, 6:18:06 PM",
            "role_id": 68779606308489,
            "server_region": "southeast_asia"
        },
        "68801081164423": {
            "crew_id": 365072236176,
            "crew_name": "Fairy Tail",
            "gender": 0,
            "last_seen": 1758793559,
            "name": "pesy",
            "registered": "Aug 14, 2022, 6:53:14 PM",
            "role_id": 68801081164423,
            "server_region": "southeast_asia"
        }
    },
    "accounts_total": 9,
    "created": 1758793559,
    "last_updated": 1758793559,
    "server_region": "southeast_asia"
}